setup.py
pyflann/__init__.py
pyflann/exceptions.py
pyflann/index.py
pyflann.egg-info/PKG-INFO
pyflann.egg-info/SOURCES.txt
pyflann.egg-info/dependency_links.txt
pyflann.egg-info/top_level.txt
pyflann/bindings/__init__.py
pyflann/bindings/flann_ctypes.py
pyflann/io/__init__.py
pyflann/io/binary_dataset.py
pyflann/io/dat_dataset.py
pyflann/io/dataset.py
pyflann/io/hdf5_dataset.py
pyflann/io/npy_dataset.py
pyflann/lib/win32/x64/flann.dll
pyflann/util/__init__.py
pyflann/util/weave_tools.py